README.md
setup.py
qito/__init__.py
qito/__main__.py
qito/main.py
qito/template.py
qito.egg-info/PKG-INFO
qito.egg-info/SOURCES.txt
qito.egg-info/dependency_links.txt
qito.egg-info/entry_points.txt
qito.egg-info/requires.txt
qito.egg-info/top_level.txt
qito/config/__init__.py
qito/config/profile.py
qito/ini/__init__.py
qito/parse/__init__.py
qito/parse/live/__init__.py
qito/parse/live/bilibili.py
qito/parse/live/douyin.py
qito/parse/music/__init__.py
qito/parse/music/qq.py
qito/parse/playlist/__init__.py
qito/parse/playlist/bilibili.py
qito/parse/playlist/ixigua.py
qito/parse/playlist/le.py
qito/parse/playlist/qq.py
qito/parse/playlist/youku.py
qito/parse/video/__init__.py
qito/parse/video/bilibili.py
qito/parse/video/cntv.py
qito/parse/video/douyin.py
qito/parse/video/fun.py
qito/parse/video/iqiyi.py
qito/parse/video/ixigua.py
qito/parse/video/le.py
qito/parse/video/mgtv.py
qito/parse/video/miguvideo.py
qito/parse/video/pptv.py
qito/parse/video/qq.py
qito/parse/video/sohu.py
qito/parse/video/wasu.py
qito/parse/video/youku.py
qito/tool/__init__.py
qito/tool/javascript/__init__.py
qito/tool/javascript/aes.js
qito/tool/javascript/iqiyi.cmd5x.js
qito/util/__init__.py
qito/util/common.py
qito/util/execute.py
qito/util/prepare.py